rust_std_t_x64_win_msvc_nightly_p2/__init__.py
rust_std_t_x64_win_msvc_nightly_p2/data/libpanic_abort-d7b21ea720e340a6.rlib
rust_std_t_x64_win_msvc_nightly_p2/data/libpanic_unwind-a3df85e0a47305bf.rlib
rust_std_t_x64_win_msvc_nightly_p2/data/librustc_demangle-5c35e7d351e4c9fd.rlib
rust_std_t_x64_win_msvc_nightly_p2/data/librustc_std_workspace_alloc-d6d39a77e4d2b597.rlib
rust_std_t_x64_win_msvc_nightly_p2/data/librustc_std_workspace_std-9d76adefd4d699f7.rlib
rust_std_t_x64_win_msvc_nightly_p2/data/libstd-e668b85dbbdbb3cf.rlib
rust_std_t_x64_win_msvc_nightly_p2/data/std-e668b85dbbdbb3cf.dll
rust_std_t_x64_win_msvc_nightly_p2/data/std-e668b85dbbdbb3cf.pdb
rust_std_t_x64_win_msvc_nightly_p2-1.91.0.dist-info/METADATA
rust_std_t_x64_win_msvc_nightly_p2-1.91.0.dist-info/WHEEL
rust_std_t_x64_win_msvc_nightly_p2-1.91.0.dist-info/top_level.txt
rust_std_t_x64_win_msvc_nightly_p2-1.91.0.dist-info/RECORD
